femto_admin/__init__.py
femto_admin/admin.py
femto_admin/constants.py
femto_admin/depends.py
femto_admin/template.py
femto_admin/statics/css/main.css
femto_admin/statics/js/list_field.js
femto_admin/statics/js/select_ajax_source.js
femto_admin/statics/placeholders/favicon.ico
femto_admin/statics/placeholders/logo/logo-primary.svg
femto_admin/statics/placeholders/logo/logo-white.svg
femto_admin/statics/placeholders/users/admin.jpg
femto_admin/statics/vendor/cookie.min.js
femto_admin/statics/vendor/DataTables/css/dataTables.css
femto_admin/statics/vendor/DataTables/css/dataTables.min.css
femto_admin/statics/vendor/DataTables/js/dataTables.bootstrap5.js
femto_admin/statics/vendor/DataTables/js/dataTables.bootstrap5.min.js
femto_admin/statics/vendor/DataTables/js/jquery.dataTables.js
femto_admin/statics/vendor/DataTables/js/jquery.dataTables.min.js
femto_admin/statics/vendor/jQuery/jquery.js
femto_admin/statics/vendor/jQuery/jquery.min.js
femto_admin/statics/vendor/select2/select2.min.css
femto_admin/statics/vendor/select2/select2.min.js
femto_admin/statics/vendor/tabler/css/tabler-icons.css
femto_admin/statics/vendor/tabler/css/tabler-icons.min.css
femto_admin/statics/vendor/tabler/css/tabler.css
femto_admin/statics/vendor/tabler/css/tabler.min.css
femto_admin/statics/vendor/tabler/css/fonts/tabler-icons.eot
femto_admin/statics/vendor/tabler/css/fonts/tabler-icons.ttf
femto_admin/statics/vendor/tabler/css/fonts/tabler-icons.woff
femto_admin/statics/vendor/tabler/css/fonts/tabler-icons.woff2
femto_admin/statics/vendor/tabler/js/dark-theme.js
femto_admin/statics/vendor/tabler/js/dark-theme.min.js
femto_admin/statics/vendor/tabler/js/tabler.js
femto_admin/statics/vendor/tabler/js/tabler.min.js
femto_admin/templates/base.html
femto_admin/templates/dashboard.html
femto_admin/templates/edit.html
femto_admin/templates/index.html
femto_admin/templates/init.html
femto_admin/templates/layout.html
femto_admin/templates/components/alert_error.html
femto_admin-0.7.4.dist-info/LICENSE
femto_admin-0.7.4.dist-info/METADATA
femto_admin-0.7.4.dist-info/WHEEL
femto_admin-0.7.4.dist-info/top_level.txt
femto_admin-0.7.4.dist-info/RECORD
