Metadata-Version: 2.1
Name: femto-admin
Version: 0.7.4
Summary: Simplest fastest minimal ASGI CRUD Admin panel for Tortoise ORM models. It's generating fully native async auto  zero config one line app
Author-email: Artemiev <mixartemev@gmail.com>
License: MIT
Project-URL: Homepage, https://github.com/XyncNet/x-admin
Project-URL: Repository, https://github.com/XyncNet/x-admin
Keywords: starlette,fastapi,admin,dashboard,datatables,crud,tortoise-orm,ASGI-admin
Requires-Python: >=3.11
License-File: LICENSE
Requires-Dist: tortoise-api
Requires-Dist: jinja2
Requires-Dist: redis
Provides-Extra: dev
Requires-Dist: build ; extra == 'dev'
Requires-Dist: twine ; extra == 'dev'
Requires-Dist: setuptools-scm ; extra == 'dev'
